LICENSE
MANIFEST.in
README.md
setup.cfg
setup.py
random_header_generator_compat/__init__.py
random_header_generator_compat/definitions.py
random_header_generator_compat/header_generator.py
random_header_generator_compat/utils.py
random_header_generator_compat.egg-info/PKG-INFO
random_header_generator_compat.egg-info/SOURCES.txt
random_header_generator_compat.egg-info/dependency_links.txt
random_header_generator_compat.egg-info/top_level.txt