Metadata-Version: 2.2
Name: random_header_generator_compat
Version: 4.0.40
Summary: random_header_generator_compat is a fork of the requests library with the playwright dependencies removed.
Home-page: https://github.com/omkarcloud/botasaurus-requests
Author: Chetan
Author-email: 53407137+Chetan11-dev@users.noreply.github.com
Maintainer: Chetan
Maintainer-email: 53407137+Chetan11-dev@users.noreply.github.com
License: MIT
Project-URL: Homepage, https://github.com/omkarcloud/botasaurus-requests
Project-URL: Bug Reports, https://github.com/omkarcloud/botasaurus-requests/issues
Project-URL: Source, https://github.com/omkarcloud/botasaurus-requests
Keywords: tls,client,http,scraping,requests,humans
Classifier: Development Status :: 3 - Alpha
Classifier: Intended Audience :: Developers
Classifier: License :: OSI Approved :: MIT License
Classifier: Topic :: Internet :: WWW/HTTP :: Browsers
Classifier: Programming Language :: Python :: 3.7
Classifier: Programming Language :: Python :: 3.8
Classifier: Programming Language :: Python :: 3.9
Classifier: Programming Language :: Python :: 3.10
Classifier: Programming Language :: Python :: 3.11
Requires-Python: >=3.5
License-File: LICENSE
Dynamic: author
Dynamic: author-email
Dynamic: classifier
Dynamic: description
Dynamic: description-content-type
Dynamic: home-page
Dynamic: keywords
Dynamic: license
Dynamic: maintainer
Dynamic: maintainer-email
Dynamic: project-url
Dynamic: requires-python
Dynamic: summary
